odoo/addons/account_invoice_validation_queued/README.rst
odoo/addons/account_invoice_validation_queued/__init__.py
odoo/addons/account_invoice_validation_queued/__manifest__.py
odoo/addons/account_invoice_validation_queued/data/queue_job.xml
odoo/addons/account_invoice_validation_queued/i18n/account_invoice_validation_queued.pot
odoo/addons/account_invoice_validation_queued/i18n/ca.po
odoo/addons/account_invoice_validation_queued/i18n/es.po
odoo/addons/account_invoice_validation_queued/i18n/fr.po
odoo/addons/account_invoice_validation_queued/i18n/it.po
odoo/addons/account_invoice_validation_queued/models/__init__.py
odoo/addons/account_invoice_validation_queued/models/account_move.py
odoo/addons/account_invoice_validation_queued/readme/CONFIGURE.rst
odoo/addons/account_invoice_validation_queued/readme/CONTRIBUTORS.rst
odoo/addons/account_invoice_validation_queued/readme/DESCRIPTION.rst
odoo/addons/account_invoice_validation_queued/readme/USAGE.rst
odoo/addons/account_invoice_validation_queued/static/description/icon.png
odoo/addons/account_invoice_validation_queued/static/description/index.html
odoo/addons/account_invoice_validation_queued/tests/__init__.py
odoo/addons/account_invoice_validation_queued/tests/test_account_invoice_validation_queued.py
odoo/addons/account_invoice_validation_queued/views/account_invoice_views.xml
odoo/addons/account_invoice_validation_queued/views/queue_job_views.xml
odoo/addons/account_invoice_validation_queued/wizards/__init__.py
odoo/addons/account_invoice_validation_queued/wizards/validate_account_move.py
odoo/addons/account_invoice_validation_queued/wizards/validate_account_move_view.xml
odoo_addon_account_invoice_validation_queued-16.0.1.0.0.6.dist-info/METADATA
odoo_addon_account_invoice_validation_queued-16.0.1.0.0.6.dist-info/WHEEL
odoo_addon_account_invoice_validation_queued-16.0.1.0.0.6.dist-info/top_level.txt
odoo_addon_account_invoice_validation_queued-16.0.1.0.0.6.dist-info/RECORD
